grafana_loki_mcp/__init__.py
grafana_loki_mcp/__main__.py
grafana_loki_mcp/__version__.py
grafana_loki_mcp/server.py
grafana_loki_mcp-0.1.4.dist-info/METADATA
grafana_loki_mcp-0.1.4.dist-info/WHEEL
grafana_loki_mcp-0.1.4.dist-info/entry_points.txt
grafana_loki_mcp-0.1.4.dist-info/licenses/LICENSE
grafana_loki_mcp-0.1.4.dist-info/RECORD
