Metadata-Version: 2.4
Name: grafana-loki-mcp
Version: 0.1.4
Summary: A FastMCP server for querying Loki logs from Grafana
Project-URL: Homepage, https://github.com/tumf/grafana-loki-mcp
Project-URL: Issues, https://github.com/tumf/grafana-loki-mcp/issues
Author-email: tumf <tumf@no-reply.github.com>
License: MIT License
License-File: LICENSE
Classifier: Development Status :: 3 - Alpha
Classifier: Intended Audience :: Developers
Classifier: License :: OSI Approved :: MIT License
Classifier: Programming Language :: Python :: 3
Classifier: Programming Language :: Python :: 3.10
Classifier: Programming Language :: Python :: 3.11
Classifier: Programming Language :: Python :: 3.12
Requires-Python: >=3.10
Requires-Dist: fastmcp>=0.1.0
Requires-Dist: requests>=2.25.0
Provides-Extra: dev
Requires-Dist: black>=23.0.0; extra == 'dev'
Requires-Dist: isort>=5.12.0; extra == 'dev'
Requires-Dist: mypy>=1.0.0; extra == 'dev'
Requires-Dist: pytest-cov>=4.0.0; extra == 'dev'
Requires-Dist: pytest>=7.0.0; extra == 'dev'
Requires-Dist: ruff>=0.0.270; extra == 'dev'
Requires-Dist: types-requests>=2.25.0; extra == 'dev'
Requires-Dist: types-setuptools; extra == 'dev'
